Metadata-Version: 2.1
Name: simplemlapp-with-ci-dvc
Version: 0.0.2
Summary: its a wine Q package
Author: shashiKumar14
License: MIT
